cf_rules/__init__.py
cf_rules/cf.py
cf_rules/error.py
cf_rules/utils.py
cf_rules-2.2.0.dist-info/licenses/LICENSE
cf_rules-2.2.0.dist-info/METADATA
cf_rules-2.2.0.dist-info/WHEEL
cf_rules-2.2.0.dist-info/top_level.txt
cf_rules-2.2.0.dist-info/RECORD
