Metadata-Version: 2.4
Name: cf_rules
Version: 2.2.0
Summary: Wrapper library to import / export multiple remote rules and easily create, modify and delete rules.
Author-email: Quentin Lienhardt <pro@quentium.fr>
License-Expression: Apache-2.0
Project-URL: Homepage, https://github.com/QuentiumYT/Cloudflare-Firewall-Rules
Project-URL: Documentation, https://quentiumyt.github.io/Cloudflare-Firewall-Rules/
Project-URL: Source Code, https://github.com/QuentiumYT/Cloudflare-Firewall-Rules
Project-URL: Bug Reports, https://github.com/QuentiumYT/Cloudflare-Firewall-Rules/issues
Keywords: api,rules,wrapper,library,firewall,waf,cloudflare,bulk
Classifier: Development Status :: 5 - Production/Stable
Classifier: Environment :: Web Environment
Classifier: Intended Audience :: Developers
Classifier: Operating System :: OS Independent
Classifier: Programming Language :: Python :: 3
Classifier: Programming Language :: Python :: 3.11
Classifier: Programming Language :: Python :: 3.12
Classifier: Programming Language :: Python :: 3.13
Classifier: Programming Language :: Python :: 3.14
Classifier: Programming Language :: Python :: 3 :: Only
Classifier: Topic :: Internet :: WWW/HTTP :: Dynamic Content
Classifier: Topic :: Software Development :: Libraries :: Python Modules
Requires-Python: >=3.11
License-File: LICENSE
Requires-Dist: requests>=2.32
Dynamic: license-file
